tap_amazon_sp/__init__.py
tap_amazon_sp/schemas/orders.json
tap_amazon_sp/streams/__init__.py
tap_amazon_sp/streams/orders.py
tap_amazon_sp-0.1.1.dist-info/LICENSE
tap_amazon_sp-0.1.1.dist-info/METADATA
tap_amazon_sp-0.1.1.dist-info/WHEEL
tap_amazon_sp-0.1.1.dist-info/entry_points.txt
tap_amazon_sp-0.1.1.dist-info/top_level.txt
tap_amazon_sp-0.1.1.dist-info/RECORD
