Metadata-Version: 2.1
Name: tap-amazon-sp
Version: 0.1.1
Summary: Singer.io tap for extracting data from Amazon Seller Partner API.
Home-page: https://github.com/vibeus/tap-amazon-sp
Author: Vibe Inc
License: UNKNOWN
Platform: UNKNOWN
Classifier: Programming Language :: Python :: 3 :: Only
License-File: LICENSE
Requires-Dist: python-amazon-sp-api
Requires-Dist: requests
Requires-Dist: singer-python
